[
  {
    "id": "77ea3c20-f502-4bd6-8b21-36c0db3c0c71",
    "data": [
      {
        "text": "it",
        "meta": "@sys.ignore",
        "userDefined": false
      },
      {
        "text": " is my ",
        "userDefined": false
      },
      {
        "text": "birthday",
        "meta": "@sys.ignore",
        "userDefined": false
      }
    ],
    "isTemplate": false,
    "count": 0,
    "updated": 0
  },
  {
    "id": "7e03cf2d-1905-4a86-99e3-828c28e618bc",
    "data": [
      {
        "text": "today",
        "meta": "@sys.ignore",
        "userDefined": false
      },
      {
        "text": " is my ",
        "userDefined": false
      },
      {
        "text": "birthday",
        "meta": "@sys.ignore",
        "userDefined": false
      }
    ],
    "isTemplate": false,
    "count": 0,
    "updated": 0
  },
  {
    "id": "508a0660-13f8-4fc7-8bc5-e7026bcf4d69",
    "data": [
      {
        "text": "I\u0027m celebrating my birthday today",
        "userDefined": false
      }
    ],
    "isTemplate": false,
    "count": 0,
    "updated": 0
  },
  {
    "id": "7f5f6769-44cf-4d1d-bdd3-cb8243a6ae58",
    "data": [
      {
        "text": "I was born today",
        "userDefined": false
      }
    ],
    "isTemplate": false,
    "count": 0,
    "updated": 0
  },
  {
    "id": "7689123f-e820-496b-a6aa-3db875f042ad",
    "data": [
      {
        "text": "it\u0027s my birthday today",
        "userDefined": false
      }
    ],
    "isTemplate": false,
    "count": 0,
    "updated": 0
  },
  {
    "id": "3707d12a-69c0-40ba-911a-e6dc1f12d6d4",
    "data": [
      {
        "text": "it\u0027s my b-day",
        "userDefined": false
      }
    ],
    "isTemplate": false,
    "count": 0,
    "updated": 0
  }
]